pinter/__init__.py
pinter/__main__.py
pinter-0.1.1.dist-info/LICENSE
pinter-0.1.1.dist-info/METADATA
pinter-0.1.1.dist-info/WHEEL
pinter-0.1.1.dist-info/entry_points.txt
pinter-0.1.1.dist-info/RECORD
